push_plan/__init__.py
push_plan/__main__.py
push_plan/config.py
push_plan/console.py
push_plan/dirs.py
push_plan/dprint.py
push_plan/publish.py
push_plan/record.py
push_plan-0.1.1.dist-info/entry_points.txt
push_plan-0.1.1.dist-info/LICENSE
push_plan-0.1.1.dist-info/WHEEL
push_plan-0.1.1.dist-info/METADATA
push_plan-0.1.1.dist-info/RECORD
