Metadata-Version: 2.1
Name: push-plan
Version: 0.1.1
Summary: Archive and publish status to finger.farm
Home-page: https://sr.ht/~gokuldas/push-plan/
License: GPL-3.0-or-later
Keywords: finger,finger.farm,status
Author: Gokul Das B
Author-email: dev@gokuldas.space
Requires-Python: >=3.10,<4.0
Classifier: Development Status :: 4 - Beta
Classifier: Intended Audience :: End Users/Desktop
Classifier: License :: OSI Approved :: GNU General Public License v3 or later (GPLv3+)
Classifier: Programming Language :: Python :: 3
Classifier: Programming Language :: Python :: 3.10
Classifier: Topic :: Internet :: Finger
Requires-Dist: requests (>=2.27.1,<3.0.0)
Requires-Dist: toml (>=0.10.2,<0.11.0)
Project-URL: Repository, https://git.sr.ht/~gokuldas/push-plan
